{
    "users": [],
    "admins": [
        {
            "name": "Luis Lizarraga",
            "email": "luis@commonsense.io",
            "password": "123macarena"
        },
        {
            "name": "Daniel Zavala",
            "email": "d@commonsense.io",
            "password": "xMLewQXLz8"
        }
    ],
    "organizations": [
        {
            "name": "Barcel",
            "description": "Organización de Barcel"
        },
        {
            "name": "Globo",
            "description": "Organización de Globo"
        }
    ],
    "roles": [
        {
            "name": "OrgAdmin",
            "isDefault": false,
            "priority": 1
        },
        {
            "name": "Analyst",
            "isDefault": false,
            "priority": 2

        },
        {
            "name": "Manager Level 3",
            "isDefault": false,
            "priority": 3

        },
        {
            "name": "Manager Level 2",
            "isDefault": false,
            "priority": 4
        },
        {
            "name": "Manager Level 1",
            "isDefault": true,
            "priority": 5
        }
    ]
}
